shareable_lock-0.1.0.dist-info/licenses/LICENSE
src/__init__.py
src/shareable_lock.py
shareable_lock-0.1.0.dist-info/METADATA
shareable_lock-0.1.0.dist-info/WHEEL
shareable_lock-0.1.0.dist-info/top_level.txt
shareable_lock-0.1.0.dist-info/RECORD
