Metadata-Version: 2.4
Name: shareable_lock
Version: 0.1.0
Summary: shareable-lock is a lock that can be shared across Python processes.
Home-page: https://github.com/natibek/shareable-lock/tree/main
Author: Nathnael Bekele
Author-email: nwtbekele@gmail.com
License: Apache 2.0
Classifier: Development Status :: 4 - Beta
Classifier: Programming Language :: Python :: 3
Classifier: Operating System :: OS Independent
Requires-Python: >=3.12.0
License-File: LICENSE
Dynamic: author
Dynamic: author-email
Dynamic: classifier
Dynamic: description
Dynamic: description-content-type
Dynamic: home-page
Dynamic: license
Dynamic: license-file
Dynamic: requires-python
Dynamic: summary
